sendJhy/__init__.py
sendJhy/sendJhy.py
sendJhy-0.0.16.dist-info/METADATA
sendJhy-0.0.16.dist-info/WHEEL
sendJhy-0.0.16.dist-info/top_level.txt
sendJhy-0.0.16.dist-info/RECORD
