Metadata-Version: 2.1
Name: sendJhy
Version: 0.0.16
Summary: 로컬 api sqlite db 사용, 교수 회원가입 및 기본 inNout 데이터 삽입, tree 변경
Home-page: UNKNOWN
Author: lucete28
Author-email: 2580jhy@naver.com
License: UNKNOWN
Keywords: Code,Lucete,lucete,lucete28,Lucete28,jhy
Platform: UNKNOWN
Classifier: Programming Language :: Python :: 3
Classifier: Programming Language :: Python :: 3.2
Classifier: Programming Language :: Python :: 3.3
Classifier: Programming Language :: Python :: 3.4
Classifier: Programming Language :: Python :: 3.5
Classifier: Programming Language :: Python :: 3.6
Classifier: Programming Language :: Python :: 3.7
Classifier: Programming Language :: Python :: 3.8
Classifier: Programming Language :: Python :: 3.9
Classifier: Programming Language :: Python :: 3.10
Classifier: Programming Language :: Python :: 3.11
Requires-Python: >=3
